[
  {
    "name": "time_to_first_favorable_5m",
    "n": 110,
    "unique": 17,
    "ic_pnl": -0.7888,
    "t_pnl": -13.335,
    "p_pnl": 0.0,
    "ic_win": -0.6922,
    "p_win": 0.0,
    "cost": "cheap",
    "effort": "small",
    "computable": true,
    "verdict": "PROMISING"
  },
  {
    "name": "consec_adverse_5m_post",
    "n": 110,
    "unique": 7,
    "ic_pnl": -0.6747,
    "t_pnl": -9.5,
    "p_pnl": 0.0,
    "ic_win": -0.6831,
    "p_win": 0.0,
    "cost": "cheap",
    "effort": "small",
    "computable": true,
    "verdict": "PROMISING"
  },
  {
    "name": "hour_of_day",
    "n": 141,
    "unique": 24,
    "ic_pnl": 0.1779,
    "t_pnl": 2.132,
    "p_pnl": 0.0348,
    "ic_win": 0.1624,
    "p_win": 0.0544,
    "cost": "cheap",
    "effort": "small",
    "computable": true,
    "verdict": "PROMISING"
  },
  {
    "name": "btc_4h_return_signed",
    "n": 141,
    "unique": 45,
    "ic_pnl": 0.1691,
    "t_pnl": 2.023,
    "p_pnl": 0.045,
    "ic_win": 0.0727,
    "p_win": 0.3914,
    "cost": "cheap",
    "effort": "small",
    "computable": true,
    "verdict": "PROMISING"
  },
  {
    "name": "vote_entropy",
    "n": 45,
    "unique": 41,
    "ic_pnl": -0.1328,
    "t_pnl": -0.879,
    "p_pnl": 0.3844,
    "ic_win": -0.0838,
    "p_win": 0.584,
    "cost": "cheap",
    "effort": "small",
    "computable": true,
    "verdict": "MAYBE"
  },
  {
    "name": "volume_zscore_4h",
    "n": 141,
    "unique": 110,
    "ic_pnl": 0.1286,
    "t_pnl": 1.529,
    "p_pnl": 0.1285,
    "ic_win": 0.0339,
    "p_win": 0.69,
    "cost": "cheap",
    "effort": "small",
    "computable": true,
    "verdict": "MAYBE"
  },
  {
    "name": "day_of_week",
    "n": 141,
    "unique": 7,
    "ic_pnl": 0.1164,
    "t_pnl": 1.382,
    "p_pnl": 0.1692,
    "ic_win": 0.154,
    "p_win": 0.0682,
    "cost": "cheap",
    "effort": "small",
    "computable": true,
    "verdict": "MAYBE"
  },
  {
    "name": "realized_vol_24h_1h",
    "n": 141,
    "unique": 50,
    "ic_pnl": -0.0974,
    "t_pnl": -1.154,
    "p_pnl": 0.2507,
    "ic_win": -0.051,
    "p_win": 0.548,
    "cost": "moderate",
    "effort": "small",
    "computable": true,
    "verdict": "WEAK"
  },
  {
    "name": "rel_strength_vs_btc_24h",
    "n": 141,
    "unique": 46,
    "ic_pnl": 0.0887,
    "t_pnl": 1.05,
    "p_pnl": 0.2954,
    "ic_win": 0.1133,
    "p_win": 0.1809,
    "cost": "cheap",
    "effort": "small",
    "computable": true,
    "verdict": "WEAK"
  },
  {
    "name": "vol_of_vol_1h",
    "n": 141,
    "unique": 50,
    "ic_pnl": -0.0742,
    "t_pnl": -0.878,
    "p_pnl": 0.3817,
    "ic_win": -0.0499,
    "p_win": 0.5569,
    "cost": "moderate",
    "effort": "small",
    "computable": true,
    "verdict": "WEAK"
  },
  {
    "name": "consecutive_regime_count",
    "n": 141,
    "unique": 6,
    "ic_pnl": 0.0451,
    "t_pnl": 0.533,
    "p_pnl": 0.5951,
    "ic_win": 0.0327,
    "p_win": 0.7001,
    "cost": "cheap",
    "effort": "small",
    "computable": true,
    "verdict": "DEAD"
  },
  {
    "name": "atr_percentile_30d",
    "n": 141,
    "unique": 46,
    "ic_pnl": -0.0445,
    "t_pnl": -0.526,
    "p_pnl": 0.6,
    "ic_win": -0.0032,
    "p_win": 0.9701,
    "cost": "moderate",
    "effort": "small",
    "computable": true,
    "verdict": "DEAD"
  },
  {
    "name": "realized_vol_4h_5m",
    "n": 141,
    "unique": 110,
    "ic_pnl": -0.0356,
    "t_pnl": -0.42,
    "p_pnl": 0.6749,
    "ic_win": 0.0395,
    "p_win": 0.6422,
    "cost": "moderate",
    "effort": "small",
    "computable": true,
    "verdict": "DEAD"
  },
  {
    "name": "wick_ratio_1h_6bar",
    "n": 141,
    "unique": 50,
    "ic_pnl": 0.0355,
    "t_pnl": 0.419,
    "p_pnl": 0.6759,
    "ic_win": 0.0919,
    "p_win": 0.2785,
    "cost": "cheap",
    "effort": "small",
    "computable": true,
    "verdict": "DEAD"
  },
  {
    "name": "time_since_prior_trade_min",
    "n": 137,
    "unique": 137,
    "ic_pnl": 0.0324,
    "t_pnl": 0.377,
    "p_pnl": 0.7066,
    "ic_win": 0.0225,
    "p_win": 0.7938,
    "cost": "cheap",
    "effort": "small",
    "computable": true,
    "verdict": "DEAD"
  },
  {
    "name": "dist_30d_mean_atr_signed",
    "n": 141,
    "unique": 52,
    "ic_pnl": -0.0224,
    "t_pnl": -0.264,
    "p_pnl": 0.7922,
    "ic_win": 0.119,
    "p_win": 0.1598,
    "cost": "moderate",
    "effort": "small",
    "computable": true,
    "verdict": "DEAD"
  },
  {
    "name": "btc_corr_4h_5m",
    "n": 76,
    "unique": 49,
    "ic_pnl": 0.0152,
    "t_pnl": 0.131,
    "p_pnl": 0.896,
    "ic_win": 0.0267,
    "p_win": 0.8188,
    "cost": "expensive",
    "effort": "medium",
    "computable": true,
    "verdict": "DEAD"
  },
  {
    "name": "session_us",
    "n": 141,
    "unique": 2,
    "ic_pnl": null,
    "t_pnl": null,
    "p_pnl": null,
    "ic_win": null,
    "p_win": null,
    "cost": "cheap",
    "effort": "small",
    "computable": true,
    "verdict": "INSUFFICIENT"
  },
  {
    "name": "session_asia",
    "n": 141,
    "unique": 2,
    "ic_pnl": null,
    "t_pnl": null,
    "p_pnl": null,
    "ic_win": null,
    "p_win": null,
    "cost": "cheap",
    "effort": "small",
    "computable": true,
    "verdict": "INSUFFICIENT"
  },
  {
    "name": "weekend",
    "n": 141,
    "unique": 2,
    "ic_pnl": null,
    "t_pnl": null,
    "p_pnl": null,
    "ic_win": null,
    "p_win": null,
    "cost": "cheap",
    "effort": "small",
    "computable": true,
    "verdict": "INSUFFICIENT"
  },
  {
    "name": "concurrent_signals_30min",
    "n": 0,
    "unique": 0,
    "ic_pnl": null,
    "t_pnl": null,
    "p_pnl": null,
    "ic_win": null,
    "p_win": null,
    "cost": "cheap",
    "effort": "small",
    "computable": true,
    "verdict": "ERROR:'Index' object has no attribute 'abs'"
  }
]